OCFit/OC_class.py
OCFit/__init__.py
OCFit/ga.py
OCFit/info_ga.py
OCFit/info_mc.py
OCFit-0.2.2.dist-info/LICENSE
OCFit-0.2.2.dist-info/METADATA
OCFit-0.2.2.dist-info/WHEEL
OCFit-0.2.2.dist-info/top_level.txt
OCFit-0.2.2.dist-info/RECORD
